{"results": [{"rule_results": {"color-checks": {"passed": "False", "histograms": {"Chi-Squared": 2000.0, "passed": {"Chi-Squared": false, "Hellinger": false, "Chi-Square-Alt": false, "Kullback-Leibler": false, "Intersection": false, "Correlation": false}, "Hellinger": 1.0, "Chi-Square-Alt": 12140.0, "Kullback-Leibler": 52781.9610587318, "Intersection": 0.0, "Correlation": -0.03136571277722799}}, "pixel-checks": {"compare_resolution": {"passed": "False", "desription": "Image a is X times smaller/greater than image b", "resolution_factors": [3.7905759162303663, 0.4914004914004914, 1.0]}, "passed": "False", "image-similarity-measures": {"passed": "False", "error": "Input images must have the same dimensions."}}, "classification-checks": {"passed": "False"}, "nan-value-check": {"nan-value-comparison": {"file_b": {"count": 0}, "file_a": {"count": 0}}, "passed": "True"}, "output-data-checks": {"passed": "False", "matching-file-extensions": true, "file-size-check": {"file_size_factor": 197.65386852821408, "passed": "False", "file_size_a": "1 MB", "file_size_b": "6 KB"}}}, "meta-information": {"performance": {"provider_b": 2.288910150527954, "unit": "seconds", "provider_a": 38.39395880699158}, "provider-job-id_b": "", "provider_a": "WWU_GEE", "file_a": "reports/Netherlands/Job-2/WWU_GEE/Netherlands-Job-2.png", "provider_b": "EURAC", "job-identifier": "Netherlands-Job-2", "provider-job-id_a": "74NuDKcuwplmovF7", "file_b": "reports/Netherlands/Job-2/EURAC/Netherlands-Job-2.png"}}]}