{"results": [{"meta-information": {"performance": {"provider_a": 18.218088150024414, "unit": "seconds", "provider_b": Infinity}, "provider-job-id_b": "", "job-identifier": "Island-Job-2", "file_a": "reports/Island/Job-2/WWU_GEE/Island-Job-2.png", "provider_a": "WWU_GEE", "file_b": "reports/Island/Job-2/EURAC/Island-Job-2.png", "provider_b": "EURAC", "provider-job-id_a": "vdttVe73CSiB1NbJ"}, "rule_results": {"description": "Validation could not be performed as atleast one provider did not return data, if there are validation results it is because local results were used", "provider_b_download_successful": false, "provider_a_download_successful": true}}]}