{"results": [{"rule_results": {"provider_b_download_successful": true, "description": "Validation could not be performed as atleast one provider did not return data, if there are validation results it is because local results were used", "provider_a_download_successful": false}, "meta-information": {"provider-job-id_b": "", "provider_a": "WWU_GEE", "provider-job-id_a": "", "performance": {"unit": "seconds", "provider_a": Infinity, "provider_b": 16.931238651275635}, "file_a": "reports/Venezuela/Job-1/WWU_GEE/Venezuela-Job-1.png", "file_b": "reports/Venezuela/Job-1/EURAC/Venezuela-Job-1.png", "job-identifier": "Venezuela-Job-1", "provider_b": "EURAC"}}]}