{"results": [{"meta-information": {"provider-job-id_a": "xZF9AYrHohlnxBjh", "job-identifier": "Venezuela-Job-1", "file_a": "reports/Venezuela/Job-1/GEE/Venezuela-Job-1.png", "file_b": "reports/Venezuela/Job-1/EURAC/Venezuela-Job-1.png", "provider_b": "EURAC", "provider-job-id_b": "", "provider_a": "GEE", "performance": {"unit": "seconds", "provider_a": 16.63524055480957, "provider_b": 15.794888973236084}}, "rule_results": {"output-data-checks": {"passed": "False", "file-size-check": {"file_size_b": "19 MB", "file_size_factor": 0.12547676249252857, "passed": "False", "file_size_a": "2 MB"}, "matching-file-extensions": true}, "nan-value-check": {"passed": "True", "nan-value-comparison": {"file_a": {"count": 0}, "file_b": {"count": 0}}}, "color-checks": {"histograms": {"passed": {"Hellinger": true, "Correlation": true, "Chi-Squared": false, "Intersection": true}, "Hellinger": 0.3828111712773692, "Correlation": 0.7842675871551323, "Chi-Squared": 22776.33367740128, "Intersection": 1538.0}, "passed": "True"}}}]}