{"results": [{"meta-information": {"performance": {"provider_a": 16.5793194770813, "provider_b": 16.619710445404053, "unit": "seconds"}, "provider-job-id_a": "w5UOLuSk4HbxvZnL", "provider_b": "WWU_GEE_COPERNICUS_S2_SR", "provider-job-id_b": "kcd3TxrAa38o8F7a", "provider_a": "WWU_GEE_COPERNICUS_S2", "job-identifier": "Uganda-Job-1", "file_b": "reports/Uganda/Job-1/WWU_GEE_COPERNICUS_S2_SR/Uganda-Job-1.png", "file_a": "reports/Uganda/Job-1/WWU_GEE_COPERNICUS_S2/Uganda-Job-1.png"}, "rule_results": {"output-data-checks": {"passed": "True", "file-size-check": {"file_size_a": "2 MB", "file_size_factor": 0.9639664335991861, "passed": "True", "file_size_b": "2 MB"}, "matching-file-extensions": true}, "classification-checks": {"passed": "True", "matching-boundaries": {"comparison-image": "comparison_image_Uganda-Job-1_Uganda-Job-1.png", "overlap-percentage": "0.46952620722649663", "passed": "True"}}, "nan-value-check": {"nan-value-comparison": {"file_b": {"count": 0}, "file_a": {"count": 0}}, "passed": "True"}, "pixel-checks": {"compare_resolution": {"desription": "Image a is X times smaller/greater than image b", "resolution_factors": [1.0, 1.0, 1.0], "passed": "True"}, "image-similarity-measures": {"passed": "True", "compare_nrmse": 0.061090082870166956, "compare_mse": 128.2133389553863, "compare_ssim": 0.9771187258743208, "compare_psnr": 27.05147150557478}, "passed": "True", "differenceImage_Path": "SSIM_Uganda-Job-1_Uganda-Job-1.png"}, "color-checks": {"histograms": {"Intersection": 1050.0, "Correlation": 0.46969692193188023, "Chi-Squared": 3877.5728656501587, "passed": {"Intersection": false, "Correlation": false, "Chi-Squared": false, "Hellinger": true}, "Hellinger": 0.4813766817193832}, "passed": "False"}}}]}