{"results": [{"meta-information": {"job-identifier": "Uganda-Job-1", "file_b": "reports/Uganda/Job-1/EURAC/Uganda-Job-1.png", "file_a": "reports/Uganda/Job-1/WWU_GEE/Uganda-Job-1.png", "provider-job-id_a": "o5TD0U09UDgh4bbD", "provider-job-id_b": "", "provider_a": "WWU_GEE", "provider_b": "EURAC", "performance": {"unit": "seconds", "provider_a": 22.84554648399353, "provider_b": 19.60125708580017}}, "rule_results": {"color-checks": {"passed": "True", "histograms": {"Correlation": 0.9769362051456616, "passed": {"Correlation": true, "Intersection": true, "Hellinger": true, "Chi-Squared": false, "Kullback-Leibler": true, "Chi-Square-Alt": true}, "Intersection": 1826.0, "Hellinger": 0.13456832690601284, "Chi-Squared": 11355.60633393928, "Kullback-Leibler": -2000.2486243710887, "Chi-Square-Alt": 4729.473081893242}}, "output-data-checks": {"matching-file-extensions": true, "passed": "False", "file-size-check": {"file_size_a": "2 MB", "file_size_b": "22 MB", "passed": "False", "file_size_factor": 0.12158756659553038}}, "nan-value-check": {"passed": "True", "nan-value-comparison": {"file_b": {"count": 0}, "file_a": {"count": 0}}}, "pixel-checks": {"image-similarity-measures": {"passed": "False", "error": "Input images must have the same dimensions."}, "passed": "False", "compare_resolution": {"resolution_factors": [0.3056234718826406, 0.3045062955599735, 1.0], "passed": "False", "desription": "Image a is X times smaller/greater than image b"}}, "classification-checks": {"passed": "False"}}}]}