{"results": [{"rule_results": {"color-checks": {"histograms": {"Correlation": 0.1216790186423589, "passed": {"Correlation": false, "Intersection": true, "Chi-Squared": false, "Hellinger": false, "Chi-Square-Alt": false, "Kullback-Leibler": true}, "Intersection": 856.0, "Chi-Squared": 1059184.5833519504, "Hellinger": 0.7211172621316041, "Chi-Square-Alt": 21071.126093772986, "Kullback-Leibler": 1602.101180660258}, "passed": "False"}, "pixel-checks": {"image-similarity-measures": {"error": "Input images must have the same dimensions.", "passed": "False"}, "compare_resolution": {"desription": "Image a is X times smaller/greater than image b", "passed": "False", "resolution_factors": [0.07198573657232003, 0.18076644974692696, 1.0]}, "passed": "False"}, "classification-checks": {"passed": "False"}, "nan-value-check": {"nan-value-comparison": {"file_b": {"count": 0}, "file_a": {"count": 0}}, "passed": "True"}, "output-data-checks": {"passed": "False", "matching-file-extensions": true, "file-size-check": {"file_size_factor": 0.010143249752636477, "passed": "False", "file_size_a": "347 KB", "file_size_b": "33 MB"}}}, "meta-information": {"provider_a": "WWU_GEE", "job-identifier": "Island-Job-1", "provider-job-id_a": "Pgwrh9RjlrzK21QJ", "file_b": "reports/Island/Job-1/EURAC/Island-Job-1.png", "file_a": "reports/Island/Job-1/WWU_GEE/Island-Job-1.png", "provider_b": "EURAC", "provider-job-id_b": "", "performance": {"provider_a": 30.349962949752808, "unit": "seconds", "provider_b": 32.33486199378967}}}]}