{"results": [{"meta-information": {"provider-job-id_b": "r9cMgMqrKUt1XszX", "performance": {"unit": "seconds", "provider_a": 16.67416024208069, "provider_b": 15.771403074264526}, "provider-job-id_a": "yOtoavqQXVKZ4XSR", "provider_a": "WWU_GEE_COPERNICUS_S2", "provider_b": "WWU_GEE_COPERNICUS_S2_SR", "file_b": "reports/Switzerland/Job-1/WWU_GEE_COPERNICUS_S2_SR/Switzerland-Job-1.png", "job-identifier": "Switzerland-Job-1", "file_a": "reports/Switzerland/Job-1/WWU_GEE_COPERNICUS_S2/Switzerland-Job-1.png"}, "rule_results": {"classification-checks": {"matching-boundaries": {"comparison-image": "comparison_image_Switzerland-Job-1_Switzerland-Job-1.png", "overlap-percentage": "0.0", "passed": "False"}, "passed": "False"}, "nan-value-check": {"passed": "True", "nan-value-comparison": {"file_b": {"count": 0}, "file_a": {"count": 0}}}, "output-data-checks": {"file-size-check": {"file_size_b": "5 KB", "file_size_a": "1 MB", "file_size_factor": 329.96565412495687, "passed": "False"}, "matching-file-extensions": true, "passed": "False"}, "color-checks": {"histograms": {"Intersection": 250.0, "Hellinger": 0.8040190354753588, "Chi-Squared": 14000.0, "passed": {"Intersection": false, "Hellinger": false, "Chi-Squared": false, "Correlation": true}, "Correlation": 0.717937795372717}, "passed": "True"}, "pixel-checks": {"image-similarity-measures": {"compare_mse": 27289.340729775664, "compare_nrmse": 1.0, "compare_ssim": 0.2869385627261255, "passed": "False", "compare_psnr": 3.770873169854446}, "differenceImage_Path": "SSIM_Switzerland-Job-1_Switzerland-Job-1.png", "passed": "False", "compare_resolution": {"resolution_factors": [1.0, 1.0, 1.0], "passed": "True", "desription": "Image a is X times smaller/greater than image b"}}}}]}